pymfx4/__init__.py
pymfx4/mfconnection.py
pymfx4/mfdatastorage.py
pymfx4/mfenums.py
pymfx4/mffullindex.py
pymfx4/mfkeyboard.py
pymfx4/mfparameters.py
pymfx4/mfx4ARMadillo.py
pymfx4/mfx4ARMadilloConfigurationDefinitions.py
pymfx4/mfx4ARMadilloEnums.py
pymfx4/mfx4device.py
pymfx4/mfx4driver.py
pymfx4/mfxdd.py
pymfx4-0.1.1.dist-info/LICENSE
pymfx4-0.1.1.dist-info/METADATA
pymfx4-0.1.1.dist-info/WHEEL
pymfx4-0.1.1.dist-info/top_level.txt
pymfx4-0.1.1.dist-info/RECORD
