Metadata-Version: 2.1
Name: pymfx4
Version: 0.1.1
Summary: Access MFX_4 devices.
Home-page: https://www.m-f.tech/
Author: Alexander Angold
Author-email: Alexander Angold <pymfx4@infodb.eu>
License: MIT License
Project-URL: Homepage, https://github.com/AAngold/pymfx4
Project-URL: Bug Tracker, https://github.com/AAngold/pymfx4/issues
Classifier: Programming Language :: Python :: 3
Classifier: License :: OSI Approved :: MIT License
Classifier: Operating System :: OS Independent
Requires-Python: >=3.7
License-File: LICENSE
Requires-Dist: serial (>=0.0.97)
Requires-Dist: jsonpickle
